{
  "schema_version": "0.2",
  "run_id": "20260704_coheronia_fq00_v0_6_1_closeout_repair",
  "project_id": "coheronia-game",
  "project_root": "B:/dev/Coheronia/coheronia_fable_oneshot_repo",
  "repo_root": "B:/dev/Coheronia/coheronia_fable_oneshot_repo",
  "branch": "main",
  "start_commit": "828aae4",
  "end_commit": "95be771",
  "run_state": "SIGNABLE",
  "started_at": "2026-07-04T11:34:00-04:00",
  "ended_at": "2026-07-04T12:10:00-04:00",
  "summary": "FQ-00 v0.6.1 closeout repair from docs/FABLE_TASK_QUEUE.md: legacy pre-v0.6 character migration now marks items_granted so role starter items cannot duplicate on top of migrated world inventory; two new fq00_* smoke checks cover the full legacy migration + regrant path (suite 122 -> 124, PASS on a fresh windowed Godot 4.6.1 run); the v0.6 outbox packets record the real closeout commit 828aae4 and manifest-aligned profiles; EOF whitespace removed from the v0.6 work-order doc. Also repaired interrupted-session file truncation (NUL-padded tails) found in the working tree.",
  "scope": "FQ-00 only; no new feature work. Repair commit 95be771 plus this evidence-only packet commit.",
  "validation_state": "pass",
  "readme_state": "unchanged",
  "variable_matrix_state": "unchanged",
  "handoff_state": "updated",
  "boh_sync_state": "queued",
  "git_state": "committed",
  "risk_level": "low",
  "next_action": "FQ-01: player health, damage, healing, and death loop.",
  "ledger_path": ".project/runs/20260704_coheronia_fq00_v0_6_1_closeout_repair.md",
  "atlas_packet_path": ".project/atlas_outbox/20260704_coheronia_fq00_v0_6_1_closeout_repair.json",
  "boh_packet_path": ".project/boh_outbox/20260704_coheronia_fq00_v0_6_1_closeout_repair.json",
  "profiles": ["public_repo", "software_project"],
  "overrides": []
}
